depot_api-1.0.9.dist-info/METADATA
depot_api-1.0.9.dist-info/WHEEL
depot_api/__init__.py
depot_api/api/__init__.py
depot_api/api/default_api.py
depot_api/api_client.py
depot_api/api_response.py
depot_api/configuration.py
depot_api/exceptions.py
depot_api/models/__init__.py
depot_api/models/client_id.py
depot_api/models/client_secret.py
depot_api/models/cluster.py
depot_api/models/cluster_in.py
depot_api/models/cluster_out.py
depot_api/models/finished_at.py
depot_api/models/grant_type.py
depot_api/models/http_validation_error.py
depot_api/models/id.py
depot_api/models/id_out.py
depot_api/models/job_instance.py
depot_api/models/job_instance_in.py
depot_api/models/job_instance_out.py
depot_api/models/log_out.py
depot_api/models/private_key.py
depot_api/models/provider.py
depot_api/models/provider_out.py
depot_api/models/provider_type.py
depot_api/models/provider_type_out.py
depot_api/models/public_key.py
depot_api/models/repository.py
depot_api/models/repository_in.py
depot_api/models/repository_key.py
depot_api/models/repository_out.py
depot_api/models/ssh_key_in.py
depot_api/models/ssh_key_out.py
depot_api/models/validation_error.py
depot_api/models/validation_error_loc_inner.py
depot_api/py.typed
depot_api/rest.py
test/__init__.py
test/test_client_id.py
test/test_client_secret.py
test/test_cluster.py
test/test_cluster_in.py
test/test_cluster_out.py
test/test_default_api.py
test/test_finished_at.py
test/test_grant_type.py
test/test_http_validation_error.py
test/test_id.py
test/test_id_out.py
test/test_job_instance.py
test/test_job_instance_in.py
test/test_job_instance_out.py
test/test_log_out.py
test/test_private_key.py
test/test_provider.py
test/test_provider_out.py
test/test_provider_type.py
test/test_provider_type_out.py
test/test_public_key.py
test/test_repository.py
test/test_repository_in.py
test/test_repository_key.py
test/test_repository_out.py
test/test_ssh_key_in.py
test/test_ssh_key_out.py
test/test_validation_error.py
test/test_validation_error_loc_inner.py
depot_api-1.0.9.dist-info/RECORD
